src/__init__.py
src/loger.py
src/main.py
areacetra-0.0.3.dist-info/METADATA
areacetra-0.0.3.dist-info/WHEEL
areacetra-0.0.3.dist-info/top_level.txt
areacetra-0.0.3.dist-info/RECORD
