Metadata-Version: 2.1
Name: areacetra
Version: 0.0.3
Summary: This is the simplest modul for calculate figure area.
Home-page: https://github.com/krimerkhex
Author: karleneg
Author-email: kolya.gar.1@gmail.com
Keywords: files main
Classifier: Programming Language :: Python :: 3.11
Classifier: License :: OSI Approved :: MIT License
Classifier: Operating System :: OS Independent
Requires-Python: >=3.11
Requires-Dist: pytest ==8.1.1
Requires-Dist: loguru ==0.7.2
